Metadata-Version: 1.1
Name: lambda-face-recognition-prebuilt
Version: 0.0.10
Summary: Prebuilt dependencies for running face_recognition in AWS Lambda
Home-page: https://github.com/jonathanporta/lambda_face_recognition_prebuilt
Author: Jonathan Porta
Author-email: jonathan@jonathanPorta.com
License: MIT
Keywords: lambda face_recognition aws_lambda
Platform: UNKNOWN
Classifier: Development Status :: 5 - Production/Stable
Classifier: Intended Audience :: Developers
Classifier: Topic :: Software Development :: Build Tools
Classifier: License :: OSI Approved :: MIT License
Classifier: Programming Language :: Python :: 3.6
